LICENSE
MANIFEST.in
README.md
setup.py
PyJSONViewer.egg-info/PKG-INFO
PyJSONViewer.egg-info/SOURCES.txt
PyJSONViewer.egg-info/dependency_links.txt
PyJSONViewer.egg-info/entry_points.txt
PyJSONViewer.egg-info/top_level.txt
pyjsonviewer/VERSION
pyjsonviewer/__init__.py
pyjsonviewer/__main__.py
pyjsonviewer/icon.png
pyjsonviewer/pyjsonviewer.py