Metadata-Version: 2.1
Name: PyJSONViewer
Version: 1.5.2
Summary: A JSON file data viewer using pure python
Home-page: https://github.com/AtsushiSakai/PyJSONViewer
Author: Atsushi Sakai
Author-email: asakaig@gmail.com
Maintainer: Atsushi Sakai
Maintainer-email: asakaig@gmail.com
License: MIT
Keywords: python json tkinter
Platform: UNKNOWN
Classifier: Programming Language :: Python :: 3
Classifier: License :: OSI Approved :: MIT License
Classifier: Topic :: Scientific/Engineering :: Visualization
Requires-Python: >3.6.0
